auraloss/__init__.py
auraloss/freq.py
auraloss/perceptual.py
auraloss/plotting.py
auraloss/time.py
auraloss/utils.py
auraloss-0.4.0.dist-info/LICENSE
auraloss-0.4.0.dist-info/METADATA
auraloss-0.4.0.dist-info/WHEEL
auraloss-0.4.0.dist-info/top_level.txt
auraloss-0.4.0.dist-info/RECORD
