Metadata-Version: 2.1
Name: auraloss
Version: 0.4.0
Summary: Collection of audio-focused loss functions in PyTorch.
Home-page: https://github.com/csteinmetz1/auraloss
Author: Christian Steinmetz
Author-email: c.j.steinmetz@qmul.ac.uk
License: Apache License 2.0
Classifier: License :: OSI Approved :: Apache Software License
Classifier: Topic :: Multimedia :: Sound/Audio
Classifier: Topic :: Scientific/Engineering
Requires-Python: >=3.6.0
Provides-Extra: test
Provides-Extra: all
License-File: LICENSE
